omuplugin_chat/__init__.py
omuplugin_chat/plugin.py
omuplugin_chat/version.py
omuplugin_chat-0.9.13.dist-info/METADATA
omuplugin_chat-0.9.13.dist-info/WHEEL
omuplugin_chat-0.9.13.dist-info/entry_points.txt
omuplugin_chat-0.9.13.dist-info/RECORD
