Metadata-Version: 2.4
Name: omuplugin_chat
Version: 0.9.13
Summary: チャットを管理するためのOMUAPPSプラグイン
Author-email: am230 <111672334+am230@users.noreply.github.com>
Requires-Python: >=3.12
Requires-Dist: iwashi>=3.1.1
Requires-Dist: loguru>=0.7.2
Requires-Dist: omu-chat>=0.9.13
